poetry_auto_export/__init__.py
poetry_auto_export/check_requirements_file.py
poetry_auto_export/plugin.py
poetry_auto_export-0.4.0.dist-info/LICENSE
poetry_auto_export-0.4.0.dist-info/METADATA
poetry_auto_export-0.4.0.dist-info/WHEEL
poetry_auto_export-0.4.0.dist-info/entry_points.txt
poetry_auto_export-0.4.0.dist-info/RECORD
