Metadata-Version: 2.3
Name: poetry-auto-export
Version: 0.4.0
Summary: Automatically create requirements.txt on every poetry lock
License: MIT
Author: Hubert Bereś
Author-email: h.beres@hotmail.com
Requires-Python: >=3.10,<4.0
Classifier: License :: OSI Approved :: MIT License
Classifier: Programming Language :: Python :: 3
Classifier: Programming Language :: Python :: 3.10
Classifier: Programming Language :: Python :: 3.11
Classifier: Programming Language :: Python :: 3.12
Classifier: Programming Language :: Python :: 3.13
Requires-Dist: poetry (>=1.6.0,<3.0.0)
Requires-Dist: poetry-plugin-export (>=1.6.0,<2.0.0)
Project-URL: Repository, https://github.com/Ddedalus/poetry-auto-export
